ANI1datatools/__init__.py
ANI1datatools/example_data_sampler.py
ANI1datatools/pyanitools.py
ANI1datatools-0.0.3.dist-info/LICENSE
ANI1datatools-0.0.3.dist-info/METADATA
ANI1datatools-0.0.3.dist-info/WHEEL
ANI1datatools-0.0.3.dist-info/top_level.txt
ANI1datatools-0.0.3.dist-info/RECORD
