Metadata-Version: 2.1
Name: ANI1datatools
Version: 0.0.3
Summary: package used to access the ANI-1 data set
Home-page: https://github.com/isayev/ANI1_dataset
License: UNKNOWN
Platform: UNKNOWN
Classifier: Programming Language :: Python :: 3
Classifier: License :: OSI Approved :: MIT License
Requires-Python: >=3.6
License-File: LICENSE
Requires-Dist: numpy
Requires-Dist: h5py
